lab_orchestrator_lib_django_adapter/__init__.py
lab_orchestrator_lib_django_adapter/adapter.py
lab_orchestrator_lib_django_adapter/admin.py
lab_orchestrator_lib_django_adapter/apps.py
lab_orchestrator_lib_django_adapter/controller_collection.py
lab_orchestrator_lib_django_adapter/models.py
lab_orchestrator_lib_django_adapter/serializers.py
lab_orchestrator_lib_django_adapter/tests.py
lab_orchestrator_lib_django_adapter/urls.py
lab_orchestrator_lib_django_adapter/views.py
lab_orchestrator_lib_django_adapter/migrations/0001_initial.py
lab_orchestrator_lib_django_adapter/migrations/0002_auto_20210928_0919.py
lab_orchestrator_lib_django_adapter/migrations/0003_auto_20210928_0922.py
lab_orchestrator_lib_django_adapter/migrations/__init__.py
lab_orchestrator_lib_django_adapter-1.0.0.dist-info/LICENSE
lab_orchestrator_lib_django_adapter-1.0.0.dist-info/METADATA
lab_orchestrator_lib_django_adapter-1.0.0.dist-info/WHEEL
lab_orchestrator_lib_django_adapter-1.0.0.dist-info/top_level.txt
lab_orchestrator_lib_django_adapter-1.0.0.dist-info/RECORD
