Metadata-Version: 2.1
Name: lab-orchestrator-lib-django-adapter
Version: 1.0.0
Summary: An adapter to use the lab orchestrator lib in django projects.
Home-page: https://github.com/LabOrchestrator/LabOrchestratorLib-DjangoAdapter
Author: Marco Schlicht
Author-email: git@privacymail.dev
License: MPL
Project-URL: Bug Tracker, https://github.com/LabOrchestrator/LabOrchestratorLib-DjangoAdapter/issues
Platform: UNKNOWN
Classifier: Programming Language :: Python :: 3
Classifier: License :: OSI Approved :: Mozilla Public License 2.0 (MPL 2.0)
Classifier: Operating System :: OS Independent
Classifier: Development Status :: 5 - Production/Stable
Requires-Python: >=3.8
License-File: LICENSE
Requires-Dist: django (==3.2.6)
Requires-Dist: djangorestframework (==3.12.4)
Requires-Dist: lab-orchestrator-lib (==1.0.0)
